atmark.py
atmark-0.5.0.dist-info/DESCRIPTION.rst
atmark-0.5.0.dist-info/entry_points.txt
atmark-0.5.0.dist-info/METADATA
atmark-0.5.0.dist-info/metadata.json
atmark-0.5.0.dist-info/RECORD
atmark-0.5.0.dist-info/top_level.txt
atmark-0.5.0.dist-info/WHEEL
